blog/__init__.py
blog/admin.py
blog/adminforms.py
blog/apis.py
blog/apps.py
blog/models.py
blog/rss.py
blog/serializers.py
blog/sitemap.py
blog/tests.py
blog/views.py
blog/middleware/__init__.py
blog/middleware/user_id.py
blog/migrations/0001_initial.py
blog/migrations/0002_auto_20220407_1021.py
blog/migrations/0003_post_content_html.py
blog/migrations/__init__.py
comment/__init__.py
comment/admin.py
comment/apps.py
comment/block.html
comment/forms.py
comment/models.py
comment/result.html
comment/tests.py
comment/views.py
comment/migrations/0001_initial.py
comment/migrations/0002_auto_20220407_1607.py
comment/migrations/__init__.py
comment/templatetags/__init__.py
comment/templatetags/comment_block.py
config/__init__.py
config/admin.py
config/apps.py
config/models.py
config/tests.py
config/views.py
config/blocks/sidebar_comments.html
config/migrations/0001_initial.py
config/migrations/__init__.py
typeidea/__init__.py
typeidea/asgi.py
typeidea/base_admin.py
typeidea/custom_site.py
typeidea/urls.py
typeidea/wsgi.py
typeidea/settings/__init__.py
typeidea/settings/base.py
typeidea/settings/develop.py
typeidea/settings/product.py
typeidea/themes/bootstrap/static/css/bootstrap.css
typeidea/themes/bootstrap/templates/blogs/base.html
typeidea/themes/bootstrap/templates/blogs/detail.html
typeidea/themes/bootstrap/templates/blogs/list.html
typeidea/themes/bootstrap/templates/config/blocks/sidebar_comments.html
typeidea/themes/bootstrap/templates/config/blocks/sidebar_posts.html
typeidea/themes/default/templates/blogs/base.html
typeidea/themes/default/templates/blogs/detail.html
typeidea/themes/default/templates/blogs/list.html
typeidea/themes/default/templates/config/links.html
typeidea/themes/default/templates/config/blocks/sidebar_comments.html
typeidea/themes/default/templates/config/blocks/sidebar_posts.html
typeidea_testing-0.7.data/scripts/manage.py
typeidea_testing-0.7.dist-info/LICENSE
typeidea_testing-0.7.dist-info/METADATA
typeidea_testing-0.7.dist-info/WHEEL
typeidea_testing-0.7.dist-info/entry_points.txt
typeidea_testing-0.7.dist-info/top_level.txt
typeidea_testing-0.7.dist-info/RECORD
