Metadata-Version: 2.1
Name: typeidea-testing
Version: 0.7
Summary: Blog System base on Django
Home-page: https://blog.csdn.net/
Author: kingOwen27
Author-email: 1209574292@qq.com
License: MIT
Platform: UNKNOWN
Classifier: Development Status :: 3 - Alpha
Classifier: Intended Audience :: Developers
Classifier: License :: OSI Approved :: MIT License
Classifier: Programming Language :: Python :: 3.6
License-File: LICENSE
Requires-Dist: django (~=1.11)
